time_server/__init__.py
time_server/main.py
time_server_mcp_yolan11-0.1.0.dist-info/licenses/LICENSE
time_server_mcp_yolan11-0.1.0.dist-info/METADATA
time_server_mcp_yolan11-0.1.0.dist-info/WHEEL
time_server_mcp_yolan11-0.1.0.dist-info/entry_points.txt
time_server_mcp_yolan11-0.1.0.dist-info/top_level.txt
time_server_mcp_yolan11-0.1.0.dist-info/RECORD
