Metadata-Version: 2.4
Name: time-server-mcp-yolan11
Version: 0.1.0
Summary: A simple MCP server that provides current time functionality
Author-email: Your Name <your.email@example.com>
Classifier: Programming Language :: Python :: 3
Classifier: License :: OSI Approved :: MIT License
Classifier: Operating System :: OS Independent
Requires-Python: >=3.8
License-File: LICENSE
Requires-Dist: pytz
Requires-Dist: mcp
Dynamic: license-file
